emoji_picker/__init__.py
emoji_picker/apps.py
emoji_picker/widgets.py
emoji_picker/static/emoji_picker/emoji-picker-main.css
emoji_picker/static/emoji_picker/emoji-picker-panel.css
emoji_picker/static/emoji_picker/emoji-picker.js
emoji_picker/static/emoji_picker/emoji-picker.js.map
emoji_picker/templates/emoji_picker/base.html
emoji_picker/templates/emoji_picker/textarea.html
emoji_picker/templates/emoji_picker/textinput.html
django_emoji_picker-0.0.6.dist-info/LICENSE
django_emoji_picker-0.0.6.dist-info/METADATA
django_emoji_picker-0.0.6.dist-info/WHEEL
django_emoji_picker-0.0.6.dist-info/top_level.txt
django_emoji_picker-0.0.6.dist-info/RECORD
