Metadata-Version: 2.1
Name: django-emoji-picker
Version: 0.0.6
Summary: Django app providing text input and textarea widgets with emoji picker
Home-page: https://github.com/wdr-data/django-emoji-picker
Author: Hacking Studio
Author-email: hello@hacking.studio
License: MIT License
Keywords: django emoji widget
Platform: UNKNOWN
Classifier: Environment :: Web Environment
Classifier: Framework :: Django
Classifier: Framework :: Django :: 2.0
Classifier: Intended Audience :: Developers
Classifier: License :: OSI Approved :: MIT License
Classifier: Operating System :: OS Independent
Classifier: Programming Language :: Python
Classifier: Programming Language :: Python :: 3.5
Classifier: Programming Language :: Python :: 3.6
Classifier: Programming Language :: Python :: 3.7
Classifier: Topic :: Internet :: WWW/HTTP
Classifier: Topic :: Internet :: WWW/HTTP :: Dynamic Content
